{"rootId":"rootShell","elements":[{"id":"rootShell","component":"div","props":{"className":"flex flex-col h-screen w-full bg-surface-container-lowest overflow-hidden"},"children":["shellHeader","shellBody"]},{"id":"shellHeader","component":"header","props":{"className":"h-12 bg-surface-container-highest shadow-sm flex-shrink-0 z-10"},"children":["hdrMainWrapper"]},{"id":"shellBody","component":"div","props":{"className":"flex-1 flex overflow-hidden"},"children":["shellAside","shellMain"]},{"id":"shellAside","component":"aside","props":{"className":"w-[15.5rem] bg-surface-container-highest shadow-sm flex-shrink-0 overflow-hidden"},"children":["sdbSidebarCol"]},{"id":"shellMain","component":"main","props":{"className":"flex-1 flex overflow-hidden"},"children":["shellFormArea","shellPreviewArea"]},{"id":"shellFormArea","component":"section","props":{"className":"flex-1 overflow-y-auto p-page"},"children":["frmStepContainer","frmBasicInfoCard","frmTargetingCard","frmBudgetCard","frmCreativeCard","frmActionBar"]},{"id":"shellPreviewArea","component":"aside","props":{"className":"w-[35%] max-w-[540px] min-w-[360px] bg-surface-container-highest border-l border-divider flex-shrink-0 overflow-y-auto"},"children":["prvRootContainer"]},{"id":"hdrMainWrapper","component":"div","props":{"className":"flex items-center h-full px-4 gap-4"},"children":["hdrLeftSection","hdrBreadcrumb","hdrRightSection"]},{"id":"hdrLeftSection","component":"div","props":{"className":"flex items-center gap-4 h-full flex-shrink-0"},"children":["hdrLogoImage","hdrMainMenu"]},{"id":"hdrLogoImage","component":"img","props":{"src":{"path":"/logoImage"},"alt":"Logo","className":"h-7 w-auto cursor-pointer"}},{"id":"hdrMainMenu","component":"Menu","props":{"mode":"horizontal","selectedKeys":{"path":"/selectedMenuKeys"},"items":{"path":"/mainMenuItems"},"className":"border-none flex-shrink-0"}},{"id":"hdrBreadcrumb","component":"Breadcrumb","props":{"items":{"path":"/breadcrumbItems"},"className":"flex-1 min-w-0 overflow-hidden whitespace-nowrap"}},{"id":"hdrRightSection","component":"div","props":{"className":"flex items-center gap-3 h-full flex-shrink-0"},"children":["hdrSaveDraftBtn","hdrPublishBtn","hdrDivider","hdrNotificationBadge","hdrUserDropdown"]},{"id":"hdrSaveDraftBtn","component":"Button","props":{"value":{"path":"/headerActions/0/btnText"},"color":{"path":"/headerActions/0/btnType"},"icon":{"path":"/headerActions/0/btnIcon"},"iconPlacement":"start"}},{"id":"hdrPublishBtn","component":"Button","props":{"value":{"path":"/headerActions/1/btnText"},"color":{"path":"/headerActions/1/btnType"},"icon":{"path":"/headerActions/1/btnIcon"},"iconPlacement":"start"}},{"id":"hdrDivider","component":"div","props":{"className":"w-px h-5 bg-divider mx-0.5"}},{"id":"hdrNotificationBadge","component":"Badge","props":{"count":{"path":"/notification/badgeCount"},"overflowCount":99},"children":["hdrNotificationIcon"]},{"id":"hdrNotificationIcon","component":"Icon","props":{"name":{"path":"/notification/bellIcon"},"shape":"outline","color":"default","className":"w-5 h-5 cursor-pointer"}},{"id":"hdrUserDropdown","component":"Dropdown","props":{"placement":"bottomRight","trigger":["click"],"menu":{"path":"/userMenuItems"}},"children":["hdrUserTrigger"]},{"id":"hdrUserTrigger","component":"div","props":{"className":"flex items-center gap-2 cursor-pointer px-2 py-1 rounded-action hover:bg-surface transition-colors"},"children":["hdrUserAvatar","hdrUserInfo","hdrUserChevron"]},{"id":"hdrUserAvatar","component":"img","props":{"src":{"path":"/userInfo/avatarImage"},"alt":"用户头像","className":"w-7 h-7 rounded-full object-cover"}},{"id":"hdrUserInfo","component":"div","props":{"className":"flex flex-col leading-tight"},"children":["hdrUserName","hdrUserRole"]},{"id":"hdrUserName","component":"span","props":{"value":{"path":"/userInfo/nickName"},"className":"text-sm font-medium text-on-surface"}},{"id":"hdrUserRole","component":"span","props":{"value":{"path":"/userInfo/roleName"},"className":"text-xs text-on-surface-variant"}},{"id":"hdrUserChevron","component":"Icon","props":{"name":"chevron-down","shape":"outline","color":"default","className":"w-4 h-4"}},{"id":"sdbSidebarCol","component":"div","props":{"className":"flex flex-col h-full"},"children":["sdbSidebarHeader","sdbSidebarMenuScroll","sdbSidebarFooter"]},{"id":"sdbSidebarHeader","component":"div","props":{"className":"flex items-center justify-between px-4 h-12 border-b border-divider flex-shrink-0"},"children":["sdbSidebarBrandWrap","sdbSidebarCollapseIcon"]},{"id":"sdbSidebarBrandWrap","component":"div","props":{"className":"flex items-center gap-2"},"children":["sdbSidebarBrandIcon","sdbSidebarBrandText"]},{"id":"sdbSidebarBrandIcon","component":"Icon","props":{"name":"rocket","color":"primary","shape":"square","className":"w-6 h-6"}},{"id":"sdbSidebarBrandText","component":"span","props":{"value":"营销平台","className":"text-lg font-semibold text-on-surface"}},{"id":"sdbSidebarCollapseIcon","component":"Icon","props":{"name":"panel-left-close","color":"default","shape":"outline","className":"w-5 h-5"}},{"id":"sdbSidebarMenuScroll","component":"div","props":{"className":"flex-1 overflow-y-auto py-2"},"children":["sdbSidebarMenu"]},{"id":"sdbSidebarMenu","component":"Menu","props":{"mode":"vertical","inlineCollapsed":false,"selectedKeys":{"path":"/selectedKeys"},"openKeys":{"path":"/openKeys"},"items":{"path":"/menuItems"},"className":"w-full border-none"}},{"id":"sdbSidebarFooter","component":"div","props":{"className":"flex items-center gap-2 px-4 py-3 border-t border-divider flex-shrink-0 cursor-pointer hover:bg-surface-variant transition-colors"},"children":["sdbSidebarHelpIcon","sdbSidebarHelpText"]},{"id":"sdbSidebarHelpIcon","component":"Icon","props":{"name":"life-buoy","color":"default","shape":"outline","className":"w-5 h-5"}},{"id":"sdbSidebarHelpText","component":"span","props":{"value":"帮助与反馈","className":"text-md text-on-surface-variant"}},{"id":"frmStepContainer","component":"div","props":{"className":"bg-surface-container-highest rounded-xl shadow-sm p-6 mb-section"},"children":["frmStepHeaderRow","frmSteps"]},{"id":"frmStepHeaderRow","component":"div","props":{"className":"flex items-center gap-2 mb-6"},"children":["frmStepIcon","frmStepTitle","frmStepCurrentTag"]},{"id":"frmStepIcon","component":"Icon","props":{"name":"workflow","color":"primary","shape":"outline","className":"w-6 h-6"}},{"id":"frmStepTitle","component":"span","props":{"value":"活动创建流程","className":"text-lg font-semibold text-on-surface"}},{"id":"frmStepCurrentTag","component":"Tag","props":{"value":"进行中","color":"processing"}},{"id":"frmSteps","component":"Steps","props":{"current":{"path":"/currentStep"}},"children":{"path":"/steps","componentId":"frmStepItem"}},{"id":"frmStepItem","component":"StepItem","props":{"title":{"path":"title"},"content":{"path":"description"},"icon":{"path":"icon"},"status":{"path":"status"}}},{"id":"frmBasicInfoCard","component":"div","props":{"className":"bg-surface-container-highest rounded-xl shadow-sm p-6 mb-section"},"children":["frmBasicHeader","frmBasicDivider","frmBasicBody"]},{"id":"frmBasicHeader","component":"div","props":{"className":"flex flex-col gap-1 mb-4"},"children":["frmBasicHeaderLeft","frmBasicDesc"]},{"id":"frmBasicHeaderLeft","component":"div","props":{"className":"flex items-center gap-2"},"children":["frmBasicIcon","frmBasicTitle"]},{"id":"frmBasicIcon","component":"Icon","props":{"name":"info","color":"primary","shape":"outline","className":"w-6 h-6"}},{"id":"frmBasicTitle","component":"span","props":{"value":"基础信息","className":"text-lg font-semibold text-on-surface"}},{"id":"frmBasicDesc","component":"span","props":{"value":"配置活动的基础识别信息与生效周期","className":"text-sm text-on-surface-variant"}},{"id":"frmBasicDivider","component":"Divider","props":{"className":"mb-5"}},{"id":"frmBasicBody","component":"div","props":{"className":"flex flex-col gap-5"},"children":["frmBasicNameField","frmBasicDescField","frmBasicTimeField","frmBasicCategoryField"]},{"id":"frmBasicNameField","component":"div","props":{"className":"flex gap-6 items-start"},"children":["frmBasicNameLabel","frmBasicNameInput"]},{"id":"frmBasicNameLabel","component":"div","props":{"className":"w-28 shrink-0 flex items-center gap-0.5 pt-1.5"},"children":["frmBasicNameLabelText","frmBasicNameLabelReq"]},{"id":"frmBasicNameLabelText","component":"span","props":{"value":"活动名称","className":"text-sm font-medium text-on-surface whitespace-nowrap"}},{"id":"frmBasicNameLabelReq","component":"span","props":{"value":"*","className":"text-sm text-error"}},{"id":"frmBasicNameInput","component":"Input","props":{"value":{"path":"/campaignName"},"placeholder":"请输入活动名称，最多30个字符","maxLength":30,"className":"flex-1"}},{"id":"frmBasicDescField","component":"div","props":{"className":"flex gap-6 items-start"},"children":["frmBasicDescLabel","frmBasicDescInput"]},{"id":"frmBasicDescLabel","component":"div","props":{"className":"w-28 shrink-0 flex items-center gap-0.5 pt-1.5"},"children":["frmBasicDescLabelText"]},{"id":"frmBasicDescLabelText","component":"span","props":{"value":"活动描述","className":"text-sm font-medium text-on-surface whitespace-nowrap"}},{"id":"frmBasicDescInput","component":"TextArea","props":{"value":{"path":"/campaignDesc"},"placeholder":"选填，用于内部备注说明","maxLength":200,"autoSize":true,"className":"flex-1"}},{"id":"frmBasicTimeField","component":"div","props":{"className":"flex gap-6 items-start"},"children":["frmBasicTimeLabel","frmBasicTimePicker"]},{"id":"frmBasicTimeLabel","component":"div","props":{"className":"w-28 shrink-0 flex items-center gap-0.5 pt-1.5"},"children":["frmBasicTimeLabelText","frmBasicTimeLabelReq"]},{"id":"frmBasicTimeLabelText","component":"span","props":{"value":"生效时间","className":"text-sm font-medium text-on-surface whitespace-nowrap"}},{"id":"frmBasicTimeLabelReq","component":"span","props":{"value":"*","className":"text-sm text-error"}},{"id":"frmBasicTimePicker","component":"DatePicker","props":{"value":{"path":"/activeTime"},"range":true,"placeholder":["开始时间","结束时间"],"format":"YYYY-MM-DD HH:mm:ss","className":"flex-1"}},{"id":"frmBasicCategoryField","component":"div","props":{"className":"flex gap-6 items-start"},"children":["frmBasicCategoryLabel","frmBasicCategorySelect"]},{"id":"frmBasicCategoryLabel","component":"div","props":{"className":"w-28 shrink-0 flex items-center gap-0.5 pt-1.5"},"children":["frmBasicCategoryLabelText","frmBasicCategoryLabelReq"]},{"id":"frmBasicCategoryLabelText","component":"span","props":{"value":"活动类目","className":"text-sm font-medium text-on-surface whitespace-nowrap"}},{"id":"frmBasicCategoryLabelReq","component":"span","props":{"value":"*","className":"text-sm text-error"}},{"id":"frmBasicCategorySelect","component":"Select","props":{"value":{"path":"/category"},"options":{"path":"/categoryOptions"},"placeholder":"请选择归属类目","showSearch":true,"className":"flex-1"}},{"id":"frmTargetingCard","component":"div","props":{"className":"bg-surface-container-highest rounded-xl shadow-sm p-6 mb-section"},"children":["frmTargetHeader","frmTargetDivider","frmTargetBody"]},{"id":"frmTargetHeader","component":"div","props":{"className":"flex flex-col gap-1 mb-4"},"children":["frmTargetHeaderLeft","frmTargetDesc"]},{"id":"frmTargetHeaderLeft","component":"div","props":{"className":"flex items-center gap-2"},"children":["frmTargetIcon","frmTargetTitle"]},{"id":"frmTargetIcon","component":"Icon","props":{"name":"target","color":"primary","shape":"outline","className":"w-6 h-6"}},{"id":"frmTargetTitle","component":"span","props":{"value":"投放设置","className":"text-lg font-semibold text-on-surface"}},{"id":"frmTargetDesc","component":"span","props":{"value":"控制活动的展示场景与受众群体","className":"text-sm text-on-surface-variant"}},{"id":"frmTargetDivider","component":"Divider","props":{"className":"mb-5"}},{"id":"frmTargetBody","component":"div","props":{"className":"flex flex-col gap-5"},"children":["frmTargetChannelsField","frmTargetGenderField","frmTargetFreqField"]},{"id":"frmTargetChannelsField","component":"div","props":{"className":"flex gap-6 items-start"},"children":["frmTargetChannelsLabel","frmTargetChannelsCheckbox"]},{"id":"frmTargetChannelsLabel","component":"div","props":{"className":"w-28 shrink-0 flex items-center gap-0.5 pt-1.5"},"children":["frmTargetChannelsLabelText","frmTargetChannelsLabelReq"]},{"id":"frmTargetChannelsLabelText","component":"span","props":{"value":"投放渠道","className":"text-sm font-medium text-on-surface whitespace-nowrap"}},{"id":"frmTargetChannelsLabelReq","component":"span","props":{"value":"*","className":"text-sm text-error"}},{"id":"frmTargetChannelsCheckbox","component":"CheckboxGroup","props":{"value":{"path":"/channels"},"options":{"path":"/channelOptions"},"className":"flex-1"}},{"id":"frmTargetGenderField","component":"div","props":{"className":"flex gap-6 items-start"},"children":["frmTargetGenderLabel","frmTargetGenderRadio"]},{"id":"frmTargetGenderLabel","component":"div","props":{"className":"w-28 shrink-0 flex items-center gap-0.5 pt-1.5"},"children":["frmTargetGenderLabelText","frmTargetGenderLabelReq"]},{"id":"frmTargetGenderLabelText","component":"span","props":{"value":"目标性别","className":"text-sm font-medium text-on-surface whitespace-nowrap"}},{"id":"frmTargetGenderLabelReq","component":"span","props":{"value":"*","className":"text-sm text-error"}},{"id":"frmTargetGenderRadio","component":"RadioGroup","props":{"value":{"path":"/targetGender"},"options":{"path":"/genderOptions"},"optionType":"button","className":"flex-1"}},{"id":"frmTargetFreqField","component":"div","props":{"className":"flex gap-6 items-center"},"children":["frmTargetFreqLabel","frmTargetFreqSwitch"]},{"id":"frmTargetFreqLabel","component":"div","props":{"className":"w-28 shrink-0 flex items-center gap-0.5"},"children":["frmTargetFreqLabelText"]},{"id":"frmTargetFreqLabelText","component":"span","props":{"value":"频次控制","className":"text-sm font-medium text-on-surface whitespace-nowrap"}},{"id":"frmTargetFreqSwitch","component":"Switch","props":{"value":{"path":"/frequencyLimit"},"checkedChildren":"已开启","unCheckedChildren":"已关闭"}},{"id":"frmBudgetCard","component":"div","props":{"className":"bg-surface-container-highest rounded-xl shadow-sm p-6 mb-section"},"children":["frmBudgetHeader","frmBudgetDivider","frmBudgetBody"]},{"id":"frmBudgetHeader","component":"div","props":{"className":"flex flex-col gap-1 mb-4"},"children":["frmBudgetHeaderLeft","frmBudgetDesc"]},{"id":"frmBudgetHeaderLeft","component":"div","props":{"className":"flex items-center gap-2"},"children":["frmBudgetIcon","frmBudgetTitle"]},{"id":"frmBudgetIcon","component":"Icon","props":{"name":"wallet","color":"primary","shape":"outline","className":"w-6 h-6"}},{"id":"frmBudgetTitle","component":"span","props":{"value":"预算与出价","className":"text-lg font-semibold text-on-surface"}},{"id":"frmBudgetDesc","component":"span","props":{"value":"设定活动预算消耗规则，控制成本","className":"text-sm text-on-surface-variant"}},{"id":"frmBudgetDivider","component":"Divider","props":{"className":"mb-5"}},{"id":"frmBudgetBody","component":"div","props":{"className":"flex flex-col gap-5"},"children":["frmBudgetTypeField","frmBudgetAmountField","frmBudgetBidField"]},{"id":"frmBudgetTypeField","component":"div","props":{"className":"flex gap-6 items-start"},"children":["frmBudgetTypeLabel","frmBudgetTypeControl"]},{"id":"frmBudgetTypeLabel","component":"div","props":{"className":"w-28 shrink-0 flex items-center gap-0.5 pt-1.5"},"children":["frmBudgetTypeLabelText","frmBudgetTypeLabelReq"]},{"id":"frmBudgetTypeLabelText","component":"span","props":{"value":"预算类型","className":"text-sm font-medium text-on-surface whitespace-nowrap"}},{"id":"frmBudgetTypeLabelReq","component":"span","props":{"value":"*","className":"text-sm text-error"}},{"id":"frmBudgetTypeControl","component":"div","props":{"className":"flex-1 flex flex-col gap-1.5"},"children":["frmBudgetTypeRadio","frmBudgetTypeHint"]},{"id":"frmBudgetTypeRadio","component":"RadioGroup","props":{"value":{"path":"/budgetType"},"options":{"path":"/budgetTypeOptions"},"optionType":"button"}},{"id":"frmBudgetTypeHint","component":"span","props":{"value":"总预算限制活动整体消耗，日预算限制单日最大消耗","className":"text-xs text-on-surface-variant"}},{"id":"frmBudgetAmountField","component":"div","props":{"className":"flex gap-6 items-start"},"children":["frmBudgetAmountLabel","frmBudgetAmountControl"]},{"id":"frmBudgetAmountLabel","component":"div","props":{"className":"w-28 shrink-0 flex items-center gap-0.5 pt-1.5"},"children":["frmBudgetAmountLabelText","frmBudgetAmountLabelReq"]},{"id":"frmBudgetAmountLabelText","component":"span","props":{"value":"预算金额","className":"text-sm font-medium text-on-surface whitespace-nowrap"}},{"id":"frmBudgetAmountLabelReq","component":"span","props":{"value":"*","className":"text-sm text-error"}},{"id":"frmBudgetAmountControl","component":"div","props":{"className":"flex-1 flex items-center gap-2"},"children":["frmBudgetAmountInput","frmBudgetAmountUnit"]},{"id":"frmBudgetAmountInput","component":"InputNumber","props":{"value":{"path":"/totalAmount"},"min":1000,"max":10000000,"controls":true,"className":"flex-1"}},{"id":"frmBudgetAmountUnit","component":"span","props":{"value":"元","className":"text-sm text-on-surface-variant"}},{"id":"frmBudgetBidField","component":"div","props":{"className":"flex gap-6 items-start"},"children":["frmBudgetBidLabel","frmBudgetBidSlider"]},{"id":"frmBudgetBidLabel","component":"div","props":{"className":"w-28 shrink-0 flex items-center gap-0.5 pt-1.5"},"children":["frmBudgetBidLabelText","frmBudgetBidLabelReq"]},{"id":"frmBudgetBidLabelText","component":"span","props":{"value":"出价策略","className":"text-sm font-medium text-on-surface whitespace-nowrap"}},{"id":"frmBudgetBidLabelReq","component":"span","props":{"value":"*","className":"text-sm text-error"}},{"id":"frmBudgetBidSlider","component":"Slider","props":{"value":{"path":"/bidStrategy"},"min":0,"max":100,"step":5,"marks":{"0":"保守","50":"均衡","100":"激进"},"input":true,"className":"flex-1"}},{"id":"frmCreativeCard","component":"div","props":{"className":"bg-surface-container-highest rounded-xl shadow-sm p-6 mb-section"},"children":["frmCreativeHeader","frmCreativeDivider","frmCreativeBody"]},{"id":"frmCreativeHeader","component":"div","props":{"className":"flex flex-col gap-1 mb-4"},"children":["frmCreativeHeaderLeft","frmCreativeDesc"]},{"id":"frmCreativeHeaderLeft","component":"div","props":{"className":"flex items-center gap-2"},"children":["frmCreativeIcon","frmCreativeTitle"]},{"id":"frmCreativeIcon","component":"Icon","props":{"name":"image","color":"primary","shape":"outline","className":"w-6 h-6"}},{"id":"frmCreativeTitle","component":"span","props":{"value":"创意素材","className":"text-lg font-semibold text-on-surface"}},{"id":"frmCreativeDesc","component":"span","props":{"value":"上传用户可见的活动广告图与文案","className":"text-sm text-on-surface-variant"}},{"id":"frmCreativeDivider","component":"Divider","props":{"className":"mb-5"}},{"id":"frmCreativeBody","component":"div","props":{"className":"flex flex-col gap-5"},"children":["frmCreativeImgField","frmCreativeAdField","frmCreativeUrlField"]},{"id":"frmCreativeImgField","component":"div","props":{"className":"flex gap-6 items-start"},"children":["frmCreativeImgLabel","frmCreativeImgControl"]},{"id":"frmCreativeImgLabel","component":"div","props":{"className":"w-28 shrink-0 flex items-center gap-0.5 pt-1.5"},"children":["frmCreativeImgLabelText","frmCreativeImgLabelReq"]},{"id":"frmCreativeImgLabelText","component":"span","props":{"value":"主推图","className":"text-sm font-medium text-on-surface whitespace-nowrap"}},{"id":"frmCreativeImgLabelReq","component":"span","props":{"value":"*","className":"text-sm text-error"}},{"id":"frmCreativeImgControl","component":"div","props":{"className":"flex-1 flex flex-col gap-2"},"children":["frmCreativeImgPreview","frmCreativeImgHint"]},{"id":"frmCreativeImgPreview","component":"div","props":{"className":"rounded-lg overflow-hidden border border-divider bg-surface-variant max-w-md"},"children":["frmCreativeImgImage"]},{"id":"frmCreativeImgImage","component":"img","props":{"src":{"path":"/mainImage"},"alt":"活动主推图预览","className":"w-full h-auto object-cover"}},{"id":"frmCreativeImgHint","component":"div","props":{"className":"flex items-center gap-1"},"children":["frmCreativeImgHintIcon","frmCreativeImgHintText"]},{"id":"frmCreativeImgHintIcon","component":"Icon","props":{"name":"circle-check","color":"success","shape":"fill","className":"w-4 h-4"}},{"id":"frmCreativeImgHintText","component":"span","props":{"value":"已上传 · 建议尺寸 750×300","className":"text-xs text-on-surface-variant"}},{"id":"frmCreativeAdField","component":"div","props":{"className":"flex gap-6 items-start"},"children":["frmCreativeAdLabel","frmCreativeAdInput"]},{"id":"frmCreativeAdLabel","component":"div","props":{"className":"w-28 shrink-0 flex items-center gap-0.5 pt-1.5"},"children":["frmCreativeAdLabelText","frmCreativeAdLabelReq"]},{"id":"frmCreativeAdLabelText","component":"span","props":{"value":"广告文案","className":"text-sm font-medium text-on-surface whitespace-nowrap"}},{"id":"frmCreativeAdLabelReq","component":"span","props":{"value":"*","className":"text-sm text-error"}},{"id":"frmCreativeAdInput","component":"Input","props":{"value":{"path":"/adTitle"},"placeholder":"请输入吸引用户的文案","prefix":"megaphone","className":"flex-1"}},{"id":"frmCreativeUrlField","component":"div","props":{"className":"flex gap-6 items-start"},"children":["frmCreativeUrlLabel","frmCreativeUrlInput"]},{"id":"frmCreativeUrlLabel","component":"div","props":{"className":"w-28 shrink-0 flex items-center gap-0.5 pt-1.5"},"children":["frmCreativeUrlLabelText","frmCreativeUrlLabelReq"]},{"id":"frmCreativeUrlLabelText","component":"span","props":{"value":"落地页链接","className":"text-sm font-medium text-on-surface whitespace-nowrap"}},{"id":"frmCreativeUrlLabelReq","component":"span","props":{"value":"*","className":"text-sm text-error"}},{"id":"frmCreativeUrlInput","component":"Input","props":{"value":{"path":"/landingUrl"},"placeholder":"https://","prefix":"link","className":"flex-1"}},{"id":"frmActionBar","component":"div","props":{"className":"flex justify-between items-center pt-2"},"children":["frmActionBarLeft","frmActionBarRight"]},{"id":"frmActionBarLeft","component":"div","props":{"className":"flex items-center gap-1.5"},"children":["frmActionBarAutoIcon","frmActionBarAutoText"]},{"id":"frmActionBarAutoIcon","component":"Icon","props":{"name":"save","color":"default","shape":"outline","className":"w-4 h-4"}},{"id":"frmActionBarAutoText","component":"span","props":{"value":"系统每30秒自动保存草稿","className":"text-sm text-on-surface-variant"}},{"id":"frmActionBarRight","component":"div","props":{"className":"flex items-center gap-3"},"children":["frmActionBarDraftBtn","frmActionBarSubmitBtn"]},{"id":"frmActionBarDraftBtn","component":"Button","props":{"value":"保存草稿","color":"default","icon":"save","iconPlacement":"start"}},{"id":"frmActionBarSubmitBtn","component":"Button","props":{"value":"提交发布","color":"primary","icon":"send","iconPlacement":"start"}},{"id":"prvRootContainer","component":"div","props":{"className":"flex flex-col min-h-full"},"children":["prvHeaderSection","prvDeviceSection","prvStatusSection"]},{"id":"prvHeaderSection","component":"div","props":{"className":"sticky top-0 z-10 bg-surface-container-highest px-4 pt-4 pb-3 border-b border-divider"},"children":["prvHeaderTitleRow","prvHeaderSegmented"]},{"id":"prvHeaderTitleRow","component":"div","props":{"className":"flex items-center justify-between mb-3"},"children":["prvHeaderTitleGroup","prvHeaderRefreshBtn"]},{"id":"prvHeaderTitleGroup","component":"div","props":{"className":"flex items-center gap-2"},"children":["prvHeaderTitleIcon","prvHeaderTitleText"]},{"id":"prvHeaderTitleIcon","component":"Icon","props":{"name":"eye","shape":"outline","color":"primary","className":"w-5 h-5"}},{"id":"prvHeaderTitleText","component":"span","props":{"value":{"path":"/cardTitle"},"className":"text-lg font-semibold text-on-surface"}},{"id":"prvHeaderRefreshBtn","component":"Button","props":{"icon":"refresh-cw","color":"default","shape":"circle"}},{"id":"prvHeaderSegmented","component":"Segmented","props":{"value":{"path":"/currentView"},"options":{"path":"/viewModes"},"block":true,"size":"medium","className":"w-full"}},{"id":"prvDeviceSection","component":"div","props":{"className":"flex-1 flex flex-col items-center justify-start px-4 py-6"},"children":["prvDeviceFrame","prvDeviceHintRow"]},{"id":"prvDeviceFrame","component":"div","props":{"className":"w-full max-w-[280px] bg-on-surface rounded-[2rem] shadow-lg p-[6px]"},"children":["prvDeviceScreen"]},{"id":"prvDeviceScreen","component":"div","props":{"className":"bg-surface-container-lowest rounded-[1.6rem] overflow-hidden flex flex-col"},"children":["prvDeviceStatusBar","prvDeviceBannerImg","prvDeviceContentArea"]},{"id":"prvDeviceStatusBar","component":"div","props":{"className":"flex items-center justify-between px-4 py-2"},"children":["prvDeviceTime","prvDeviceStatusIcons"]},{"id":"prvDeviceTime","component":"span","props":{"value":"9:41","className":"text-xs font-semibold text-on-surface"}},{"id":"prvDeviceStatusIcons","component":"div","props":{"className":"flex items-center gap-1"},"children":["prvDeviceSignalIcon","prvDeviceWifiIcon","prvDeviceBatteryIcon"]},{"id":"prvDeviceSignalIcon","component":"Icon","props":{"name":"signal","shape":"outline","className":"w-3 h-3"}},{"id":"prvDeviceWifiIcon","component":"Icon","props":{"name":"wifi","shape":"outline","className":"w-3 h-3"}},{"id":"prvDeviceBatteryIcon","component":"Icon","props":{"name":"battery-full","shape":"outline","className":"w-3 h-3"}},{"id":"prvDeviceBannerImg","component":"img","props":{"src":{"path":"/bannerImage"},"alt":"Campaign Banner","className":"w-full h-auto object-cover block"}},{"id":"prvDeviceContentArea","component":"div","props":{"className":"p-4 flex flex-col gap-2"},"children":["prvDeviceTitle","prvDeviceSubText","prvDeviceCtaBtn"]},{"id":"prvDeviceTitle","component":"span","props":{"value":{"path":"/adTitleText"},"className":"text-sm font-bold text-on-surface leading-snug"}},{"id":"prvDeviceSubText","component":"span","props":{"value":{"path":"/adSubText"},"className":"text-xs text-on-surface-variant leading-relaxed"}},{"id":"prvDeviceCtaBtn","component":"Button","props":{"value":{"path":"/ctaText"},"color":"primary","shape":"round","className":"w-full mt-1"}},{"id":"prvDeviceHintRow","component":"div","props":{"className":"flex items-center gap-1.5 mt-4"},"children":["prvDeviceHintIcon","prvDeviceHintText"]},{"id":"prvDeviceHintIcon","component":"Icon","props":{"name":{"path":"/deviceFrameIcon"},"shape":"outline","className":"w-4 h-4"}},{"id":"prvDeviceHintText","component":"span","props":{"value":"实时同步预览","className":"text-xs text-on-surface-variant"}},{"id":"prvStatusSection","component":"div","props":{"className":"border-t border-divider px-4 py-4"},"children":["prvStatusHeader","prvStatusTagList"]},{"id":"prvStatusHeader","component":"div","props":{"className":"flex items-center gap-2 mb-3"},"children":["prvStatusHeaderIcon","prvStatusHeaderText"]},{"id":"prvStatusHeaderIcon","component":"Icon","props":{"name":"shield-check","shape":"outline","color":"success","className":"w-4 h-4"}},{"id":"prvStatusHeaderText","component":"span","props":{"value":"预检状态","className":"text-sm font-medium text-on-surface"}},{"id":"prvStatusTagList","component":"div","props":{"className":"flex flex-wrap gap-2"},"children":{"path":"/statusTags","componentId":"prvStatusTag"}},{"id":"prvStatusTag","component":"Tag","props":{"value":{"path":"text"},"color":{"path":"color"},"icon":{"path":"icon"},"size":"medium"}}],"state":{"logoImage":"https://fpoimg.com/120x40?gradient=0067D1,E6F2FD&text_color=ffffff&text=LOGO","mainMenuItems":[{"title":"工作台","key":"dashboard"},{"title":"营销中心","key":"campaign"},{"title":"用户管理","key":"user"}],"selectedMenuKeys":["campaign"],"breadcrumbItems":[{"title":"营销中心","href":"/campaign"},{"title":"活动列表","href":"/campaign/list"},{"title":"新建活动"}],"headerActions":[{"btnKey":"saveDraft","btnText":"保存草稿","btnType":"default","btnIcon":"save"},{"btnKey":"publish","btnText":"发布活动","btnType":"primary","btnIcon":"rocket"}],"notification":{"bellIcon":"bell","badgeCount":5},"userInfo":{"avatarImage":"https://randomuser.me/api/portraits/women/44.jpg","nickName":"林小溪","roleName":"运营主管"},"userMenuItems":[{"label":"个人中心","key":"profile","icon":"user"},{"label":"账号设置","key":"settings","icon":"settings"},{"label":"退出登录","key":"logout","icon":"log-out"}],"selectedKeys":["new-campaign"],"openKeys":["campaign-center"],"menuItems":[{"title":"数据概览","key":"overview","icon":"layout-dashboard"},{"title":"营销中心","key":"campaign-center","icon":"megaphone","children":[{"title":"活动管理","key":"campaign-list"},{"title":"新建活动","key":"new-campaign"},{"title":"素材中心","key":"material-lib"}]},{"title":"人群管理","key":"user-group","icon":"users"},{"title":"财务结算","key":"finance","icon":"wallet"},{"title":"系统设置","key":"settings","icon":"settings"}],"currentStep":1,"steps":[{"title":"填写信息","description":"完善活动基本配置","icon":"file-text","status":"process"},{"title":"提交审核","description":"风控与合规校验","icon":"shield-check","status":"wait"},{"title":"配置完成","description":"正式上线投放","icon":"rocket","status":"wait"}],"campaignName":"2026年春季新品发布会预热","campaignDesc":"针对3月份即将发布的旗舰机型进行全网预热，主要目标是提升品牌曝光与新品预约转化率。","activeTime":["2026-03-01 00:00:00","2026-03-15 23:59:59"],"category":"electronics","categoryOptions":[{"label":"3C数码","value":"electronics"},{"label":"美妆护肤","value":"beauty"},{"label":"服饰鞋包","value":"fashion"},{"label":"生鲜食品","value":"food"}],"channels":["app_home","search","push"],"channelOptions":[{"label":"App首页推荐流","value":"app_home"},{"label":"搜索结果页","value":"search"},{"label":"消息推送","value":"push"},{"label":"支付成功页","value":"payment_success"}],"targetGender":"all","genderOptions":[{"label":"男性","value":"male"},{"label":"女性","value":"female"},{"label":"不限","value":"all"}],"frequencyLimit":true,"budgetType":"total","budgetTypeOptions":[{"label":"总预算","value":"total"},{"label":"日预算","value":"daily"}],"totalAmount":500000,"bidStrategy":65,"mainImage":"https://fpoimg.com/750x300?gradient=0067D1,004EA8&text_color=ffffff&text=Campaign+Banner","adTitle":"科技前沿，未来已来，立即预约","landingUrl":"https://event.example.com/spring2026","currentView":"mobile","cardTitle":"效果预览","viewModes":[{"label":"手机端","value":"mobile","isActive":true},{"label":"平板端","value":"pad","isActive":false}],"deviceFrameIcon":"smartphone","bannerImage":"https://fpoimg.com/750x300?gradient=0067D1,004EA8&text_color=ffffff&text=Campaign+Banner","adTitleText":"科技前沿，未来已来，立即预约","adSubText":"2026年春季新品发布会预热","ctaText":"立即参与","statusTags":[{"color":"success","text":"图片大小达标","icon":"circle-check"},{"color":"processing","text":"预估加载: 120ms","icon":"zap"},{"color":"warning","text":"文案待优化","icon":"triangle-alert"}]}}